<!--
;; ==============================================================================
;; <auto-generated>
;;     This file was generated by a tool.
;;     Runtime Version: 2.17941.31104.49410
;;
;;     Changes to this file may cause incorrect behavior and will be lost if
;;     the code is regenerated.
;; </auto-generated>
;; <usage>
;;     This file contains the bare bones skeleton doc comments info that the
;;     generated code files refer to. If the orginal source contained comments,
;;     those comments are generated here as the "remarks" element to aid in
;;     completing the docs. This always generated file is created with a .g.xml
;;     extension, however the generated C# code includes the form with the ".g"
;;     in the extension. This prevents the generation of this skeleton from
;;     overwriting any customized docs data. Any new entries need merging into
;;     the real version with all the manual edits.
;; </usage>
;; ==============================================================================
-->
<LibLlvmAPI>
    <Enumeration name="LibLLVMDwarfSourceLanguage">
        <summary>TODO: Provide summary for LibLLVMDwarfSourceLanguage Enumeration</summary>
        <Item name="LibLLVMDwarfSourceLanguageC89">
            <summary>TODO: Provide summary for LibLLVMDwarfSourceLanguage.LibLLVMDwarfSourceLanguageC89 Enumeration</summary>
        </Item>
        <Item name="LibLLVMDwarfSourceLanguageC">
            <summary>TODO: Provide summary for LibLLVMDwarfSourceLanguage.LibLLVMDwarfSourceLanguageC Enumeration</summary>
        </Item>
        <Item name="LibLLVMDwarfSourceLanguageAda83">
            <summary>TODO: Provide summary for LibLLVMDwarfSourceLanguage.LibLLVMDwarfSourceLanguageAda83 Enumeration</summary>
        </Item>
        <Item name="LibLLVMDwarfSourceLanguageC_plus_plus">
            <summary>TODO: Provide summary for LibLLVMDwarfSourceLanguage.LibLLVMDwarfSourceLanguageC_plus_plus Enumeration</summary>
        </Item>
        <Item name="LibLLVMDwarfSourceLanguageCobol74">
            <summary>TODO: Provide summary for LibLLVMDwarfSourceLanguage.LibLLVMDwarfSourceLanguageCobol74 Enumeration</summary>
        </Item>
        <Item name="LibLLVMDwarfSourceLanguageCobol85">
            <summary>TODO: Provide summary for LibLLVMDwarfSourceLanguage.LibLLVMDwarfSourceLanguageCobol85 Enumeration</summary>
        </Item>
        <Item name="LibLLVMDwarfSourceLanguageFortran77">
            <summary>TODO: Provide summary for LibLLVMDwarfSourceLanguage.LibLLVMDwarfSourceLanguageFortran77 Enumeration</summary>
        </Item>
        <Item name="LibLLVMDwarfSourceLanguageFortran90">
            <summary>TODO: Provide summary for LibLLVMDwarfSourceLanguage.LibLLVMDwarfSourceLanguageFortran90 Enumeration</summary>
        </Item>
        <Item name="LibLLVMDwarfSourceLanguagePascal83">
            <summary>TODO: Provide summary for LibLLVMDwarfSourceLanguage.LibLLVMDwarfSourceLanguagePascal83 Enumeration</summary>
        </Item>
        <Item name="LibLLVMDwarfSourceLanguageModula2">
            <summary>TODO: Provide summary for LibLLVMDwarfSourceLanguage.LibLLVMDwarfSourceLanguageModula2 Enumeration</summary>
        </Item>
        <Item name="LibLLVMDwarfSourceLanguageJava">
            <summary>TODO: Provide summary for LibLLVMDwarfSourceLanguage.LibLLVMDwarfSourceLanguageJava Enumeration</summary>
        </Item>
        <Item name="LibLLVMDwarfSourceLanguageC99">
            <summary>TODO: Provide summary for LibLLVMDwarfSourceLanguage.LibLLVMDwarfSourceLanguageC99 Enumeration</summary>
        </Item>
        <Item name="LibLLVMDwarfSourceLanguageAda95">
            <summary>TODO: Provide summary for LibLLVMDwarfSourceLanguage.LibLLVMDwarfSourceLanguageAda95 Enumeration</summary>
        </Item>
        <Item name="LibLLVMDwarfSourceLanguageFortran95">
            <summary>TODO: Provide summary for LibLLVMDwarfSourceLanguage.LibLLVMDwarfSourceLanguageFortran95 Enumeration</summary>
        </Item>
        <Item name="LibLLVMDwarfSourceLanguagePLI">
            <summary>TODO: Provide summary for LibLLVMDwarfSourceLanguage.LibLLVMDwarfSourceLanguagePLI Enumeration</summary>
        </Item>
        <Item name="LibLLVMDwarfSourceLanguageObjC">
            <summary>TODO: Provide summary for LibLLVMDwarfSourceLanguage.LibLLVMDwarfSourceLanguageObjC Enumeration</summary>
        </Item>
        <Item name="LibLLVMDwarfSourceLanguageObjC_plus_plus">
            <summary>TODO: Provide summary for LibLLVMDwarfSourceLanguage.LibLLVMDwarfSourceLanguageObjC_plus_plus Enumeration</summary>
        </Item>
        <Item name="LibLLVMDwarfSourceLanguageUPC">
            <summary>TODO: Provide summary for LibLLVMDwarfSourceLanguage.LibLLVMDwarfSourceLanguageUPC Enumeration</summary>
        </Item>
        <Item name="LibLLVMDwarfSourceLanguageD">
            <summary>TODO: Provide summary for LibLLVMDwarfSourceLanguage.LibLLVMDwarfSourceLanguageD Enumeration</summary>
        </Item>
        <Item name="LibLLVMDwarfSourceLanguagePython">
            <summary>TODO: Provide summary for LibLLVMDwarfSourceLanguage.LibLLVMDwarfSourceLanguagePython Enumeration</summary>
        </Item>
        <Item name="LibLLVMDwarfSourceLanguageOpenCL">
            <summary>TODO: Provide summary for LibLLVMDwarfSourceLanguage.LibLLVMDwarfSourceLanguageOpenCL Enumeration</summary>
        </Item>
        <Item name="LibLLVMDwarfSourceLanguageGo">
            <summary>TODO: Provide summary for LibLLVMDwarfSourceLanguage.LibLLVMDwarfSourceLanguageGo Enumeration</summary>
        </Item>
        <Item name="LibLLVMDwarfSourceLanguageModula3">
            <summary>TODO: Provide summary for LibLLVMDwarfSourceLanguage.LibLLVMDwarfSourceLanguageModula3 Enumeration</summary>
        </Item>
        <Item name="LibLLVMDwarfSourceLanguageHaskell">
            <summary>TODO: Provide summary for LibLLVMDwarfSourceLanguage.LibLLVMDwarfSourceLanguageHaskell Enumeration</summary>
        </Item>
        <Item name="LibLLVMDwarfSourceLanguageC_plus_plus_03">
            <summary>TODO: Provide summary for LibLLVMDwarfSourceLanguage.LibLLVMDwarfSourceLanguageC_plus_plus_03 Enumeration</summary>
        </Item>
        <Item name="LibLLVMDwarfSourceLanguageC_plus_plus_11">
            <summary>TODO: Provide summary for LibLLVMDwarfSourceLanguage.LibLLVMDwarfSourceLanguageC_plus_plus_11 Enumeration</summary>
        </Item>
        <Item name="LibLLVMDwarfSourceLanguageOCaml">
            <summary>TODO: Provide summary for LibLLVMDwarfSourceLanguage.LibLLVMDwarfSourceLanguageOCaml Enumeration</summary>
        </Item>
        <Item name="LibLLVMDwarfSourceLanguageRust">
            <summary>TODO: Provide summary for LibLLVMDwarfSourceLanguage.LibLLVMDwarfSourceLanguageRust Enumeration</summary>
        </Item>
        <Item name="LibLLVMDwarfSourceLanguageC11">
            <summary>TODO: Provide summary for LibLLVMDwarfSourceLanguage.LibLLVMDwarfSourceLanguageC11 Enumeration</summary>
        </Item>
        <Item name="LibLLVMDwarfSourceLanguageSwift">
            <summary>TODO: Provide summary for LibLLVMDwarfSourceLanguage.LibLLVMDwarfSourceLanguageSwift Enumeration</summary>
        </Item>
        <Item name="LibLLVMDwarfSourceLanguageJulia">
            <summary>TODO: Provide summary for LibLLVMDwarfSourceLanguage.LibLLVMDwarfSourceLanguageJulia Enumeration</summary>
        </Item>
        <Item name="LibLLVMDwarfSourceLanguageDylan">
            <summary>TODO: Provide summary for LibLLVMDwarfSourceLanguage.LibLLVMDwarfSourceLanguageDylan Enumeration</summary>
        </Item>
        <Item name="LibLLVMDwarfSourceLanguageC_plus_plus_14">
            <summary>TODO: Provide summary for LibLLVMDwarfSourceLanguage.LibLLVMDwarfSourceLanguageC_plus_plus_14 Enumeration</summary>
        </Item>
        <Item name="LibLLVMDwarfSourceLanguageFortran03">
            <summary>TODO: Provide summary for LibLLVMDwarfSourceLanguage.LibLLVMDwarfSourceLanguageFortran03 Enumeration</summary>
        </Item>
        <Item name="LibLLVMDwarfSourceLanguageFortran08">
            <summary>TODO: Provide summary for LibLLVMDwarfSourceLanguage.LibLLVMDwarfSourceLanguageFortran08 Enumeration</summary>
        </Item>
        <Item name="LibLLVMDwarfSourceLanguageRenderScript">
            <summary>TODO: Provide summary for LibLLVMDwarfSourceLanguage.LibLLVMDwarfSourceLanguageRenderScript Enumeration</summary>
        </Item>
        <Item name="LibLLVMDwarfSourceLanguageBLISS">
            <summary>TODO: Provide summary for LibLLVMDwarfSourceLanguage.LibLLVMDwarfSourceLanguageBLISS Enumeration</summary>
        </Item>
        <Item name="LibLLVMDwarfSourceLanguageMips_Assembler">
            <summary>TODO: Provide summary for LibLLVMDwarfSourceLanguage.LibLLVMDwarfSourceLanguageMips_Assembler Enumeration</summary>
        </Item>
        <Item name="LibLLVMDwarfSourceLanguageGOOGLE_RenderScript">
            <summary>TODO: Provide summary for LibLLVMDwarfSourceLanguage.LibLLVMDwarfSourceLanguageGOOGLE_RenderScript Enumeration</summary>
        </Item>
        <Item name="LibLLVMDwarfSourceLanguageBORLAND_Delphi">
            <summary>TODO: Provide summary for LibLLVMDwarfSourceLanguage.LibLLVMDwarfSourceLanguageBORLAND_Delphi Enumeration</summary>
        </Item>
    </Enumeration>
    <Function name="LibLLVMDIBuilderCreateEnumeratorValue">
        <summary>TODO: Provide summary for Function LibLLVMDIBuilderCreateEnumeratorValue</summary>
        <param name="D">TODO: Provide details of parameter D</param>
        <param name="Name">TODO: Provide details of parameter Name</param>
        <param name="Val">TODO: Provide details of parameter Val</param>
        <returns>TODO: Document return value</returns>
    </Function>
    <Function name="LibLLVMDIBuilderCreateCompileUnit">
        <summary>TODO: Provide summary for Function LibLLVMDIBuilderCreateCompileUnit</summary>
        <param name="Builder">TODO: Provide details of parameter Builder</param>
        <param name="Lang">TODO: Provide details of parameter Lang</param>
        <param name="FileRef">TODO: Provide details of parameter FileRef</param>
        <param name="Producer">TODO: Provide details of parameter Producer</param>
        <param name="ProducerLen">TODO: Provide details of parameter ProducerLen</param>
        <param name="isOptimized">TODO: Provide details of parameter isOptimized</param>
        <param name="Flags">TODO: Provide details of parameter Flags</param>
        <param name="FlagsLen">TODO: Provide details of parameter FlagsLen</param>
        <param name="RuntimeVer">TODO: Provide details of parameter RuntimeVer</param>
        <param name="SplitName">TODO: Provide details of parameter SplitName</param>
        <param name="SplitNameLen">TODO: Provide details of parameter SplitNameLen</param>
        <param name="Kind">TODO: Provide details of parameter Kind</param>
        <param name="DWOId">TODO: Provide details of parameter DWOId</param>
        <param name="SplitDebugInlining">TODO: Provide details of parameter SplitDebugInlining</param>
        <param name="DebugInfoForProfiling">TODO: Provide details of parameter DebugInfoForProfiling</param>
        <returns>TODO: Document return value</returns>
    </Function>
</LibLlvmAPI>
