<!--
;; ==============================================================================
;; <auto-generated>
;;     This file was generated by a tool.
;;     Runtime Version: 2.17941.31104.49410
;;
;;     Changes to this file may cause incorrect behavior and will be lost if
;;     the code is regenerated.
;; </auto-generated>
;; <usage>
;;     This file contains the bare bones skeleton doc comments info that the
;;     generated code files refer to. If the orginal source contained comments,
;;     those comments are generated here as the "remarks" element to aid in
;;     completing the docs. This always generated file is created with a .g.xml
;;     extension, however the generated C# code includes the form with the ".g"
;;     in the extension. This prevents the generation of this skeleton from
;;     overwriting any customized docs data. Any new entries need merging into
;;     the real version with all the manual edits.
;; </usage>
;; ==============================================================================
-->
<LibLlvmAPI>
    <Function name="LLVMLoadLibraryPermanently">
        <summary>TODO: Provide summary for Function LLVMLoadLibraryPermanently</summary>
        <param name="Filename">TODO: Provide details of parameter Filename</param>
        <returns>TODO: Document return value</returns>
    </Function>
    <Function name="LLVMParseCommandLineOptions">
        <summary>TODO: Provide summary for Function LLVMParseCommandLineOptions</summary>
        <param name="argc">TODO: Provide details of parameter argc</param>
        <param name="argv">TODO: Provide details of parameter argv</param>
        <param name="Overview">TODO: Provide details of parameter Overview</param>
    </Function>
    <Function name="LLVMSearchForAddressOfSymbol">
        <summary>TODO: Provide summary for Function LLVMSearchForAddressOfSymbol</summary>
        <param name="symbolName">TODO: Provide details of parameter symbolName</param>
        <returns>TODO: Document return value</returns>
    </Function>
    <Function name="LLVMAddSymbol">
        <summary>TODO: Provide summary for Function LLVMAddSymbol</summary>
        <param name="symbolName">TODO: Provide details of parameter symbolName</param>
        <param name="symbolValue">TODO: Provide details of parameter symbolValue</param>
    </Function>
</LibLlvmAPI>
