<?xml version="1.0" encoding="utf-8"?><HelpTOCNode Title="Llvm.NET" Url="html/N_Llvm_NET.htm"><HelpTOCNode Title="AlignmentInfo Class" Url="html/T_Llvm_NET_AlignmentInfo.htm" HasChildren="true" /><HelpTOCNode Title="AttributeKind Enumeration" Url="html/T_Llvm_NET_AttributeKind.htm" /><HelpTOCNode Title="ByteOrdering Enumeration" Url="html/T_Llvm_NET_ByteOrdering.htm" /><HelpTOCNode Title="CallingConvention Enumeration" Url="html/T_Llvm_NET_CallingConvention.htm" /><HelpTOCNode Title="CodeGenFileType Enumeration" Url="html/T_Llvm_NET_CodeGenFileType.htm" /><HelpTOCNode Title="CodeGenOpt Enumeration" Url="html/T_Llvm_NET_CodeGenOpt.htm" /><HelpTOCNode Title="CodeModel Enumeration" Url="html/T_Llvm_NET_CodeModel.htm" /><HelpTOCNode Title="Context Class" Url="html/T_Llvm_NET_Context.htm" HasChildren="true" /><HelpTOCNode Title="ExtensiblePropertyDescriptor(T) Class" Url="html/T_Llvm_NET_ExtensiblePropertyDescriptor_1.htm" HasChildren="true" /><HelpTOCNode Title="FunctionAttributeIndex Enumeration" Url="html/T_Llvm_NET_FunctionAttributeIndex.htm" /><HelpTOCNode Title="GlobalPassRegistry Class" Url="html/T_Llvm_NET_GlobalPassRegistry.htm" HasChildren="true" /><HelpTOCNode Title="IExtensiblePropertyContainer Interface" Url="html/T_Llvm_NET_IExtensiblePropertyContainer.htm" HasChildren="true" /><HelpTOCNode Title="InstructionBuilder Class" Url="html/T_Llvm_NET_InstructionBuilder.htm" HasChildren="true" /><HelpTOCNode Title="InternalCodeGeneratorException Class" Url="html/T_Llvm_NET_InternalCodeGeneratorException.htm" HasChildren="true" /><HelpTOCNode Title="IntPredicate Enumeration" Url="html/T_Llvm_NET_IntPredicate.htm" /><HelpTOCNode Title="Linkage Enumeration" Url="html/T_Llvm_NET_Linkage.htm" /><HelpTOCNode Title="LinkerMode Enumeration" Url="html/T_Llvm_NET_LinkerMode.htm" /><HelpTOCNode Title="MDNode Class" Url="html/T_Llvm_NET_MDNode.htm" HasChildren="true" /><HelpTOCNode Title="MDString Class" Url="html/T_Llvm_NET_MDString.htm" HasChildren="true" /><HelpTOCNode Title="MemoryBuffer Class" Url="html/T_Llvm_NET_MemoryBuffer.htm" HasChildren="true" /><HelpTOCNode Title="Metadata Class" Url="html/T_Llvm_NET_Metadata.htm" HasChildren="true" /><HelpTOCNode Title="MetadataAsValue Class" Url="html/T_Llvm_NET_MetadataAsValue.htm" HasChildren="true" /><HelpTOCNode Title="MetadataKind Enumeration" Url="html/T_Llvm_NET_MetadataKind.htm" /><HelpTOCNode Title="Module Class" Url="html/T_Llvm_NET_Module.htm" HasChildren="true" /><HelpTOCNode Title="ModuleFlagBehavior Enumeration" Url="html/T_Llvm_NET_ModuleFlagBehavior.htm" /><HelpTOCNode Title="Opcode Enumeration" Url="html/T_Llvm_NET_Opcode.htm" /><HelpTOCNode Title="PassManagerBuilder Class" Url="html/T_Llvm_NET_PassManagerBuilder.htm" HasChildren="true" /><HelpTOCNode Title="Predicate Enumeration" Url="html/T_Llvm_NET_Predicate.htm" /><HelpTOCNode Title="RealPredicate Enumeration" Url="html/T_Llvm_NET_RealPredicate.htm" /><HelpTOCNode Title="Reloc Enumeration" Url="html/T_Llvm_NET_Reloc.htm" /><HelpTOCNode Title="ScalarEnumerable Class" Url="html/T_Llvm_NET_ScalarEnumerable.htm" HasChildren="true" /><HelpTOCNode Title="SizeAndAlignment Class" Url="html/T_Llvm_NET_SizeAndAlignment.htm" HasChildren="true" /><HelpTOCNode Title="StaticState Class" Url="html/T_Llvm_NET_StaticState.htm" HasChildren="true" /><HelpTOCNode Title="Target Class" Url="html/T_Llvm_NET_Target.htm" HasChildren="true" /><HelpTOCNode Title="TargetData Class" Url="html/T_Llvm_NET_TargetData.htm" HasChildren="true" /><HelpTOCNode Title="TargetMachine Class" Url="html/T_Llvm_NET_TargetMachine.htm" HasChildren="true" /><HelpTOCNode Title="TargetRegistration Enumeration" Url="html/T_Llvm_NET_TargetRegistration.htm" /><HelpTOCNode Title="TypeKind Enumeration" Url="html/T_Llvm_NET_TypeKind.htm" /><HelpTOCNode Title="Visibility Enumeration" Url="html/T_Llvm_NET_Visibility.htm" /></HelpTOCNode>